{"nodes": [{"id": "nodelinkexportertest", "label": "NodeLinkExporterTest.kt", "file_type": "code", "source_file": "app\\src\\test\\java\\com\\kunk\\singbox\\repository\\config\\NodeLinkExporterTest.kt", "source_location": "L1"}, {"id": "nodelinkexportertest_nodelinkexportertest", "label": "NodeLinkExporterTest", "file_type": "code", "source_file": "app\\src\\test\\java\\com\\kunk\\singbox\\repository\\config\\NodeLinkExporterTest.kt", "source_location": "L13"}, {"id": "nodelinkexportertest_nodelinkexportertest_exportnaiveshouldusenewfields", "label": ".exportNaiveShouldUseNewFields()", "file_type": "code", "source_file": "app\\src\\test\\java\\com\\kunk\\singbox\\repository\\config\\NodeLinkExporterTest.kt", "source_location": "L17"}, {"id": "nodelinkexportertest_nodelinkexportertest_exportnaiveshouldpreferquiccongestioncontrol", "label": ".exportNaiveShouldPreferQuicCongestionControl()", "file_type": "code", "source_file": "app\\src\\test\\java\\com\\kunk\\singbox\\repository\\config\\NodeLinkExporterTest.kt", "source_location": "L46"}, {"id": "nodelinkexportertest_nodelinkexportertest_exportvlessshouldpreservecustomencryption", "label": ".exportVlessShouldPreserveCustomEncryption()", "file_type": "code", "source_file": "app\\src\\test\\java\\com\\kunk\\singbox\\repository\\config\\NodeLinkExporterTest.kt", "source_location": "L70"}], "edges": [{"source": "nodelinkexportertest", "target": "nodelinkexportertest_nodelinkexportertest", "relation": "contains", "confidence": "EXTRACTED", "source_file": "app\\src\\test\\java\\com\\kunk\\singbox\\repository\\config\\NodeLinkExporterTest.kt", "source_location": "L13", "weight": 1.0}, {"source": "nodelinkexportertest_nodelinkexportertest", "target": "nodelinkexportertest_nodelinkexportertest_exportnaiveshouldusenewfields", "relation": "method", "confidence": "EXTRACTED", "source_file": "app\\src\\test\\java\\com\\kunk\\singbox\\repository\\config\\NodeLinkExporterTest.kt", "source_location": "L17", "weight": 1.0}, {"source": "nodelinkexportertest_nodelinkexportertest", "target": "nodelinkexportertest_nodelinkexportertest_exportnaiveshouldpreferquiccongestioncontrol", "relation": "method", "confidence": "EXTRACTED", "source_file": "app\\src\\test\\java\\com\\kunk\\singbox\\repository\\config\\NodeLinkExporterTest.kt", "source_location": "L46", "weight": 1.0}, {"source": "nodelinkexportertest_nodelinkexportertest", "target": "nodelinkexportertest_nodelinkexportertest_exportvlessshouldpreservecustomencryption", "relation": "method", "confidence": "EXTRACTED", "source_file": "app\\src\\test\\java\\com\\kunk\\singbox\\repository\\config\\NodeLinkExporterTest.kt", "source_location": "L70", "weight": 1.0}]}