{"nodes": [{"id": "dnsresolvestoretest", "label": "DnsResolveStoreTest.kt", "file_type": "code", "source_file": "app\\src\\test\\java\\com\\kunk\\singbox\\utils\\dns\\DnsResolveStoreTest.kt", "source_location": "L1"}, {"id": "dnsresolvestoretest_dnsresolvestoretest", "label": "DnsResolveStoreTest", "file_type": "code", "source_file": "app\\src\\test\\java\\com\\kunk\\singbox\\utils\\dns\\DnsResolveStoreTest.kt", "source_location": "L9"}, {"id": "dnsresolvestoretest_dnsresolvestoretest_testresolvedentry_notexpired", "label": ".testResolvedEntry_notExpired()", "file_type": "code", "source_file": "app\\src\\test\\java\\com\\kunk\\singbox\\utils\\dns\\DnsResolveStoreTest.kt", "source_location": "L13"}, {"id": "dnsresolvestoretest_dnsresolvestoretest_testresolvedentry_expired", "label": ".testResolvedEntry_expired()", "file_type": "code", "source_file": "app\\src\\test\\java\\com\\kunk\\singbox\\utils\\dns\\DnsResolveStoreTest.kt", "source_location": "L25"}, {"id": "dnsresolvestoretest_dnsresolvestoretest_testresolvedentry_almostexpired", "label": ".testResolvedEntry_almostExpired()", "file_type": "code", "source_file": "app\\src\\test\\java\\com\\kunk\\singbox\\utils\\dns\\DnsResolveStoreTest.kt", "source_location": "L37"}, {"id": "dnsresolvestoretest_dnsresolvestoretest_testresolvedentry_defaultttl", "label": ".testResolvedEntry_defaultTtl()", "file_type": "code", "source_file": "app\\src\\test\\java\\com\\kunk\\singbox\\utils\\dns\\DnsResolveStoreTest.kt", "source_location": "L49"}, {"id": "dnsresolvestoretest_dnsresolvestoretest_testdefaultttl", "label": ".testDefaultTtl()", "file_type": "code", "source_file": "app\\src\\test\\java\\com\\kunk\\singbox\\utils\\dns\\DnsResolveStoreTest.kt", "source_location": "L61"}], "edges": [{"source": "dnsresolvestoretest", "target": "dnsresolvestoretest_dnsresolvestoretest", "relation": "contains", "confidence": "EXTRACTED", "source_file": "app\\src\\test\\java\\com\\kunk\\singbox\\utils\\dns\\DnsResolveStoreTest.kt", "source_location": "L9", "weight": 1.0}, {"source": "dnsresolvestoretest_dnsresolvestoretest", "target": "dnsresolvestoretest_dnsresolvestoretest_testresolvedentry_notexpired", "relation": "method", "confidence": "EXTRACTED", "source_file": "app\\src\\test\\java\\com\\kunk\\singbox\\utils\\dns\\DnsResolveStoreTest.kt", "source_location": "L13", "weight": 1.0}, {"source": "dnsresolvestoretest_dnsresolvestoretest", "target": "dnsresolvestoretest_dnsresolvestoretest_testresolvedentry_expired", "relation": "method", "confidence": "EXTRACTED", "source_file": "app\\src\\test\\java\\com\\kunk\\singbox\\utils\\dns\\DnsResolveStoreTest.kt", "source_location": "L25", "weight": 1.0}, {"source": "dnsresolvestoretest_dnsresolvestoretest", "target": "dnsresolvestoretest_dnsresolvestoretest_testresolvedentry_almostexpired", "relation": "method", "confidence": "EXTRACTED", "source_file": "app\\src\\test\\java\\com\\kunk\\singbox\\utils\\dns\\DnsResolveStoreTest.kt", "source_location": "L37", "weight": 1.0}, {"source": "dnsresolvestoretest_dnsresolvestoretest", "target": "dnsresolvestoretest_dnsresolvestoretest_testresolvedentry_defaultttl", "relation": "method", "confidence": "EXTRACTED", "source_file": "app\\src\\test\\java\\com\\kunk\\singbox\\utils\\dns\\DnsResolveStoreTest.kt", "source_location": "L49", "weight": 1.0}, {"source": "dnsresolvestoretest_dnsresolvestoretest", "target": "dnsresolvestoretest_dnsresolvestoretest_testdefaultttl", "relation": "method", "confidence": "EXTRACTED", "source_file": "app\\src\\test\\java\\com\\kunk\\singbox\\utils\\dns\\DnsResolveStoreTest.kt", "source_location": "L61", "weight": 1.0}]}