{"nodes": [{"id": "vpnstatestore", "label": "VpnStateStore.kt", "file_type": "code", "source_file": "app\\src\\main\\java\\com\\kunk\\singbox\\ipc\\VpnStateStore.kt", "source_location": "L1"}, {"id": "vpnstatestore_vpnstatestore", "label": "VpnStateStore", "file_type": "code", "source_file": "app\\src\\main\\java\\com\\kunk\\singbox\\ipc\\VpnStateStore.kt", "source_location": "L11"}, {"id": "vpnstatestore_coremode", "label": "CoreMode", "file_type": "code", "source_file": "app\\src\\main\\java\\com\\kunk\\singbox\\ipc\\VpnStateStore.kt", "source_location": "L37"}, {"id": "vpnstatestore_vpnstatestore_getactive", "label": ".getActive()", "file_type": "code", "source_file": "app\\src\\main\\java\\com\\kunk\\singbox\\ipc\\VpnStateStore.kt", "source_location": "L47"}, {"id": "vpnstatestore_vpnstatestore_setactive", "label": ".setActive()", "file_type": "code", "source_file": "app\\src\\main\\java\\com\\kunk\\singbox\\ipc\\VpnStateStore.kt", "source_location": "L49"}, {"id": "vpnstatestore_vpnstatestore_getpending", "label": ".getPending()", "file_type": "code", "source_file": "app\\src\\main\\java\\com\\kunk\\singbox\\ipc\\VpnStateStore.kt", "source_location": "L53"}, {"id": "vpnstatestore_vpnstatestore_setpending", "label": ".setPending()", "file_type": "code", "source_file": "app\\src\\main\\java\\com\\kunk\\singbox\\ipc\\VpnStateStore.kt", "source_location": "L55"}, {"id": "vpnstatestore_vpnstatestore_getactivelabel", "label": ".getActiveLabel()", "file_type": "code", "source_file": "app\\src\\main\\java\\com\\kunk\\singbox\\ipc\\VpnStateStore.kt", "source_location": "L59"}, {"id": "vpnstatestore_vpnstatestore_setactivelabel", "label": ".setActiveLabel()", "file_type": "code", "source_file": "app\\src\\main\\java\\com\\kunk\\singbox\\ipc\\VpnStateStore.kt", "source_location": "L61"}, {"id": "vpnstatestore_vpnstatestore_getlasterror", "label": ".getLastError()", "file_type": "code", "source_file": "app\\src\\main\\java\\com\\kunk\\singbox\\ipc\\VpnStateStore.kt", "source_location": "L65"}, {"id": "vpnstatestore_vpnstatestore_setlasterror", "label": ".setLastError()", "file_type": "code", "source_file": "app\\src\\main\\java\\com\\kunk\\singbox\\ipc\\VpnStateStore.kt", "source_location": "L67"}, {"id": "vpnstatestore_vpnstatestore_ismanuallystopped", "label": ".isManuallyStopped()", "file_type": "code", "source_file": "app\\src\\main\\java\\com\\kunk\\singbox\\ipc\\VpnStateStore.kt", "source_location": "L71"}, {"id": "vpnstatestore_vpnstatestore_setmanuallystopped", "label": ".setManuallyStopped()", "file_type": "code", "source_file": "app\\src\\main\\java\\com\\kunk\\singbox\\ipc\\VpnStateStore.kt", "source_location": "L73"}, {"id": "vpnstatestore_vpnstatestore_getlastmanualstopatms", "label": ".getLastManualStopAtMs()", "file_type": "code", "source_file": "app\\src\\main\\java\\com\\kunk\\singbox\\ipc\\VpnStateStore.kt", "source_location": "L80"}, {"id": "vpnstatestore_vpnstatestore_getmode", "label": ".getMode()", "file_type": "code", "source_file": "app\\src\\main\\java\\com\\kunk\\singbox\\ipc\\VpnStateStore.kt", "source_location": "L82"}, {"id": "vpnstatestore_vpnstatestore_setmode", "label": ".setMode()", "file_type": "code", "source_file": "app\\src\\main\\java\\com\\kunk\\singbox\\ipc\\VpnStateStore.kt", "source_location": "L87"}, {"id": "vpnstatestore_vpnstatestore_getlastappmode", "label": ".getLastAppMode()", "file_type": "code", "source_file": "app\\src\\main\\java\\com\\kunk\\singbox\\ipc\\VpnStateStore.kt", "source_location": "L91"}, {"id": "vpnstatestore_vpnstatestore_setlastappmode", "label": ".setLastAppMode()", "file_type": "code", "source_file": "app\\src\\main\\java\\com\\kunk\\singbox\\ipc\\VpnStateStore.kt", "source_location": "L93"}, {"id": "vpnstatestore_vpnstatestore_getlastallowlisthash", "label": ".getLastAllowlistHash()", "file_type": "code", "source_file": "app\\src\\main\\java\\com\\kunk\\singbox\\ipc\\VpnStateStore.kt", "source_location": "L97"}, {"id": "vpnstatestore_vpnstatestore_setlastallowlisthash", "label": ".setLastAllowlistHash()", "file_type": "code", "source_file": "app\\src\\main\\java\\com\\kunk\\singbox\\ipc\\VpnStateStore.kt", "source_location": "L99"}, {"id": "vpnstatestore_vpnstatestore_getlastblocklisthash", "label": ".getLastBlocklistHash()", "file_type": "code", "source_file": "app\\src\\main\\java\\com\\kunk\\singbox\\ipc\\VpnStateStore.kt", "source_location": "L103"}, {"id": "vpnstatestore_vpnstatestore_setlastblocklisthash", "label": ".setLastBlocklistHash()", "file_type": "code", "source_file": "app\\src\\main\\java\\com\\kunk\\singbox\\ipc\\VpnStateStore.kt", "source_location": "L105"}, {"id": "vpnstatestore_vpnstatestore_saveperappvpnsettings", "label": ".savePerAppVpnSettings()", "file_type": "code", "source_file": "app\\src\\main\\java\\com\\kunk\\singbox\\ipc\\VpnStateStore.kt", "source_location": "L109"}, {"id": "vpnstatestore_vpnstatestore_hasperappvpnsettingschanged", "label": ".hasPerAppVpnSettingsChanged()", "file_type": "code", "source_file": "app\\src\\main\\java\\com\\kunk\\singbox\\ipc\\VpnStateStore.kt", "source_location": "L115"}, {"id": "vpnstatestore_vpnstatestore_savetunsettings", "label": ".saveTunSettings()", "file_type": "code", "source_file": "app\\src\\main\\java\\com\\kunk\\singbox\\ipc\\VpnStateStore.kt", "source_location": "L138"}, {"id": "vpnstatestore_vpnstatestore_hastunsettingschanged", "label": ".hasTunSettingsChanged()", "file_type": "code", "source_file": "app\\src\\main\\java\\com\\kunk\\singbox\\ipc\\VpnStateStore.kt", "source_location": "L143"}, {"id": "vpnstatestore_vpnstatestore_computetunsettingshash", "label": ".computeTunSettingsHash()", "file_type": "code", "source_file": "app\\src\\main\\java\\com\\kunk\\singbox\\ipc\\VpnStateStore.kt", "source_location": "L161"}, {"id": "vpnstatestore_vpnstatestore_shouldtriggerpreparerestart", "label": ".shouldTriggerPrepareRestart()", "file_type": "code", "source_file": "app\\src\\main\\java\\com\\kunk\\singbox\\ipc\\VpnStateStore.kt", "source_location": "L181"}, {"id": "vpnstatestore_vpnstatestore_gettrafficcleartimestamp", "label": ".getTrafficClearTimestamp()", "file_type": "code", "source_file": "app\\src\\main\\java\\com\\kunk\\singbox\\ipc\\VpnStateStore.kt", "source_location": "L193"}, {"id": "vpnstatestore_vpnstatestore_settrafficcleartimestamp", "label": ".setTrafficClearTimestamp()", "file_type": "code", "source_file": "app\\src\\main\\java\\com\\kunk\\singbox\\ipc\\VpnStateStore.kt", "source_location": "L195"}, {"id": "vpnstatestore_vpnstatestore_getlastautofailoveratms", "label": ".getLastAutoFailoverAtMs()", "file_type": "code", "source_file": "app\\src\\main\\java\\com\\kunk\\singbox\\ipc\\VpnStateStore.kt", "source_location": "L199"}, {"id": "vpnstatestore_vpnstatestore_setlastautofailoveratms", "label": ".setLastAutoFailoverAtMs()", "file_type": "code", "source_file": "app\\src\\main\\java\\com\\kunk\\singbox\\ipc\\VpnStateStore.kt", "source_location": "L201"}, {"id": "vpnstatestore_vpnstatestore_getautofailoverwindowstartatms", "label": ".getAutoFailoverWindowStartAtMs()", "file_type": "code", "source_file": "app\\src\\main\\java\\com\\kunk\\singbox\\ipc\\VpnStateStore.kt", "source_location": "L205"}, {"id": "vpnstatestore_vpnstatestore_setautofailoverwindowstartatms", "label": ".setAutoFailoverWindowStartAtMs()", "file_type": "code", "source_file": "app\\src\\main\\java\\com\\kunk\\singbox\\ipc\\VpnStateStore.kt", "source_location": "L207"}, {"id": "vpnstatestore_vpnstatestore_getautofailovercountinwindow", "label": ".getAutoFailoverCountInWindow()", "file_type": "code", "source_file": "app\\src\\main\\java\\com\\kunk\\singbox\\ipc\\VpnStateStore.kt", "source_location": "L211"}, {"id": "vpnstatestore_vpnstatestore_setautofailovercountinwindow", "label": ".setAutoFailoverCountInWindow()", "file_type": "code", "source_file": "app\\src\\main\\java\\com\\kunk\\singbox\\ipc\\VpnStateStore.kt", "source_location": "L213"}, {"id": "vpnstatestore_vpnstatestore_getautofailoverquarantinedtags", "label": ".getAutoFailoverQuarantinedTags()", "file_type": "code", "source_file": "app\\src\\main\\java\\com\\kunk\\singbox\\ipc\\VpnStateStore.kt", "source_location": "L217"}, {"id": "vpnstatestore_vpnstatestore_setautofailoverquarantinedtags", "label": ".setAutoFailoverQuarantinedTags()", "file_type": "code", "source_file": "app\\src\\main\\java\\com\\kunk\\singbox\\ipc\\VpnStateStore.kt", "source_location": "L219"}, {"id": "vpnstatestore_vpnstatestore_getlastautofailovernodetag", "label": ".getLastAutoFailoverNodeTag()", "file_type": "code", "source_file": "app\\src\\main\\java\\com\\kunk\\singbox\\ipc\\VpnStateStore.kt", "source_location": "L223"}, {"id": "vpnstatestore_vpnstatestore_setlastautofailovernodetag", "label": ".setLastAutoFailoverNodeTag()", "file_type": "code", "source_file": "app\\src\\main\\java\\com\\kunk\\singbox\\ipc\\VpnStateStore.kt", "source_location": "L225"}, {"id": "vpnstatestore_vpnstatestore_clear", "label": ".clear()", "file_type": "code", "source_file": "app\\src\\main\\java\\com\\kunk\\singbox\\ipc\\VpnStateStore.kt", "source_location": "L229"}, {"id": "vpnstatestore_vpnstatestore_clearall", "label": ".clearAll()", "file_type": "code", "source_file": "app\\src\\main\\java\\com\\kunk\\singbox\\ipc\\VpnStateStore.kt", "source_location": "L234"}, {"id": "vpnstatestore_vpnstatestore_clearconfig", "label": ".clearConfig()", "file_type": "code", "source_file": "app\\src\\main\\java\\com\\kunk\\singbox\\ipc\\VpnStateStore.kt", "source_location": "L239"}, {"id": "vpnstatestore_vpnstatestore_clearruntimestate", "label": ".clearRuntimeState()", "file_type": "code", "source_file": "app\\src\\main\\java\\com\\kunk\\singbox\\ipc\\VpnStateStore.kt", "source_location": "L259"}, {"id": "vpnstatestore_vpnstatestore_clearautofailoverruntimestate", "label": ".clearAutoFailoverRuntimeState()", "file_type": "code", "source_file": "app\\src\\main\\java\\com\\kunk\\singbox\\ipc\\VpnStateStore.kt", "source_location": "L270"}], "edges": [{"source": "vpnstatestore", "target": "vpnstatestore_vpnstatestore", "relation": "contains", "confidence": "EXTRACTED", "source_file": "app\\src\\main\\java\\com\\kunk\\singbox\\ipc\\VpnStateStore.kt", "source_location": "L11", "weight": 1.0}, {"source": "vpnstatestore", "target": "vpnstatestore_coremode", "relation": "contains", "confidence": "EXTRACTED", "source_file": "app\\src\\main\\java\\com\\kunk\\singbox\\ipc\\VpnStateStore.kt", "source_location": "L37", "weight": 1.0}, {"source": "vpnstatestore_vpnstatestore", "target": "vpnstatestore_vpnstatestore_getactive", "relation": "method", "confidence": "EXTRACTED", "source_file": "app\\src\\main\\java\\com\\kunk\\singbox\\ipc\\VpnStateStore.kt", "source_location": "L47", "weight": 1.0}, {"source": "vpnstatestore_vpnstatestore", "target": "vpnstatestore_vpnstatestore_setactive", "relation": "method", "confidence": "EXTRACTED", "source_file": "app\\src\\main\\java\\com\\kunk\\singbox\\ipc\\VpnStateStore.kt", "source_location": "L49", "weight": 1.0}, {"source": "vpnstatestore_vpnstatestore", "target": "vpnstatestore_vpnstatestore_getpending", "relation": "method", "confidence": "EXTRACTED", "source_file": "app\\src\\main\\java\\com\\kunk\\singbox\\ipc\\VpnStateStore.kt", "source_location": "L53", "weight": 1.0}, {"source": "vpnstatestore_vpnstatestore", "target": "vpnstatestore_vpnstatestore_setpending", "relation": "method", "confidence": "EXTRACTED", "source_file": "app\\src\\main\\java\\com\\kunk\\singbox\\ipc\\VpnStateStore.kt", "source_location": "L55", "weight": 1.0}, {"source": "vpnstatestore_vpnstatestore", "target": "vpnstatestore_vpnstatestore_getactivelabel", "relation": "method", "confidence": "EXTRACTED", "source_file": "app\\src\\main\\java\\com\\kunk\\singbox\\ipc\\VpnStateStore.kt", "source_location": "L59", "weight": 1.0}, {"source": "vpnstatestore_vpnstatestore", "target": "vpnstatestore_vpnstatestore_setactivelabel", "relation": "method", "confidence": "EXTRACTED", "source_file": "app\\src\\main\\java\\com\\kunk\\singbox\\ipc\\VpnStateStore.kt", "source_location": "L61", "weight": 1.0}, {"source": "vpnstatestore_vpnstatestore", "target": "vpnstatestore_vpnstatestore_getlasterror", "relation": "method", "confidence": "EXTRACTED", "source_file": "app\\src\\main\\java\\com\\kunk\\singbox\\ipc\\VpnStateStore.kt", "source_location": "L65", "weight": 1.0}, {"source": "vpnstatestore_vpnstatestore", "target": "vpnstatestore_vpnstatestore_setlasterror", "relation": "method", "confidence": "EXTRACTED", "source_file": "app\\src\\main\\java\\com\\kunk\\singbox\\ipc\\VpnStateStore.kt", "source_location": "L67", "weight": 1.0}, {"source": "vpnstatestore_vpnstatestore", "target": "vpnstatestore_vpnstatestore_ismanuallystopped", "relation": "method", "confidence": "EXTRACTED", "source_file": "app\\src\\main\\java\\com\\kunk\\singbox\\ipc\\VpnStateStore.kt", "source_location": "L71", "weight": 1.0}, {"source": "vpnstatestore_vpnstatestore", "target": "vpnstatestore_vpnstatestore_setmanuallystopped", "relation": "method", "confidence": "EXTRACTED", "source_file": "app\\src\\main\\java\\com\\kunk\\singbox\\ipc\\VpnStateStore.kt", "source_location": "L73", "weight": 1.0}, {"source": "vpnstatestore_vpnstatestore", "target": "vpnstatestore_vpnstatestore_getlastmanualstopatms", "relation": "method", "confidence": "EXTRACTED", "source_file": "app\\src\\main\\java\\com\\kunk\\singbox\\ipc\\VpnStateStore.kt", "source_location": "L80", "weight": 1.0}, {"source": "vpnstatestore_vpnstatestore", "target": "vpnstatestore_vpnstatestore_getmode", "relation": "method", "confidence": "EXTRACTED", "source_file": "app\\src\\main\\java\\com\\kunk\\singbox\\ipc\\VpnStateStore.kt", "source_location": "L82", "weight": 1.0}, {"source": "vpnstatestore_vpnstatestore", "target": "vpnstatestore_vpnstatestore_setmode", "relation": "method", "confidence": "EXTRACTED", "source_file": "app\\src\\main\\java\\com\\kunk\\singbox\\ipc\\VpnStateStore.kt", "source_location": "L87", "weight": 1.0}, {"source": "vpnstatestore_vpnstatestore", "target": "vpnstatestore_vpnstatestore_getlastappmode", "relation": "method", "confidence": "EXTRACTED", "source_file": "app\\src\\main\\java\\com\\kunk\\singbox\\ipc\\VpnStateStore.kt", "source_location": "L91", "weight": 1.0}, {"source": "vpnstatestore_vpnstatestore", "target": "vpnstatestore_vpnstatestore_setlastappmode", "relation": "method", "confidence": "EXTRACTED", "source_file": "app\\src\\main\\java\\com\\kunk\\singbox\\ipc\\VpnStateStore.kt", "source_location": "L93", "weight": 1.0}, {"source": "vpnstatestore_vpnstatestore", "target": "vpnstatestore_vpnstatestore_getlastallowlisthash", "relation": "method", "confidence": "EXTRACTED", "source_file": "app\\src\\main\\java\\com\\kunk\\singbox\\ipc\\VpnStateStore.kt", "source_location": "L97", "weight": 1.0}, {"source": "vpnstatestore_vpnstatestore", "target": "vpnstatestore_vpnstatestore_setlastallowlisthash", "relation": "method", "confidence": "EXTRACTED", "source_file": "app\\src\\main\\java\\com\\kunk\\singbox\\ipc\\VpnStateStore.kt", "source_location": "L99", "weight": 1.0}, {"source": "vpnstatestore_vpnstatestore", "target": "vpnstatestore_vpnstatestore_getlastblocklisthash", "relation": "method", "confidence": "EXTRACTED", "source_file": "app\\src\\main\\java\\com\\kunk\\singbox\\ipc\\VpnStateStore.kt", "source_location": "L103", "weight": 1.0}, {"source": "vpnstatestore_vpnstatestore", "target": "vpnstatestore_vpnstatestore_setlastblocklisthash", "relation": "method", "confidence": "EXTRACTED", "source_file": "app\\src\\main\\java\\com\\kunk\\singbox\\ipc\\VpnStateStore.kt", "source_location": "L105", "weight": 1.0}, {"source": "vpnstatestore_vpnstatestore", "target": "vpnstatestore_vpnstatestore_saveperappvpnsettings", "relation": "method", "confidence": "EXTRACTED", "source_file": "app\\src\\main\\java\\com\\kunk\\singbox\\ipc\\VpnStateStore.kt", "source_location": "L109", "weight": 1.0}, {"source": "vpnstatestore_vpnstatestore", "target": "vpnstatestore_vpnstatestore_hasperappvpnsettingschanged", "relation": "method", "confidence": "EXTRACTED", "source_file": "app\\src\\main\\java\\com\\kunk\\singbox\\ipc\\VpnStateStore.kt", "source_location": "L115", "weight": 1.0}, {"source": "vpnstatestore_vpnstatestore", "target": "vpnstatestore_vpnstatestore_savetunsettings", "relation": "method", "confidence": "EXTRACTED", "source_file": "app\\src\\main\\java\\com\\kunk\\singbox\\ipc\\VpnStateStore.kt", "source_location": "L138", "weight": 1.0}, {"source": "vpnstatestore_vpnstatestore", "target": "vpnstatestore_vpnstatestore_hastunsettingschanged", "relation": "method", "confidence": "EXTRACTED", "source_file": "app\\src\\main\\java\\com\\kunk\\singbox\\ipc\\VpnStateStore.kt", "source_location": "L143", "weight": 1.0}, {"source": "vpnstatestore_vpnstatestore", "target": "vpnstatestore_vpnstatestore_computetunsettingshash", "relation": "method", "confidence": "EXTRACTED", "source_file": "app\\src\\main\\java\\com\\kunk\\singbox\\ipc\\VpnStateStore.kt", "source_location": "L161", "weight": 1.0}, {"source": "vpnstatestore_vpnstatestore", "target": "vpnstatestore_vpnstatestore_shouldtriggerpreparerestart", "relation": "method", "confidence": "EXTRACTED", "source_file": "app\\src\\main\\java\\com\\kunk\\singbox\\ipc\\VpnStateStore.kt", "source_location": "L181", "weight": 1.0}, {"source": "vpnstatestore_vpnstatestore", "target": "vpnstatestore_vpnstatestore_gettrafficcleartimestamp", "relation": "method", "confidence": "EXTRACTED", "source_file": "app\\src\\main\\java\\com\\kunk\\singbox\\ipc\\VpnStateStore.kt", "source_location": "L193", "weight": 1.0}, {"source": "vpnstatestore_vpnstatestore", "target": "vpnstatestore_vpnstatestore_settrafficcleartimestamp", "relation": "method", "confidence": "EXTRACTED", "source_file": "app\\src\\main\\java\\com\\kunk\\singbox\\ipc\\VpnStateStore.kt", "source_location": "L195", "weight": 1.0}, {"source": "vpnstatestore_vpnstatestore", "target": "vpnstatestore_vpnstatestore_getlastautofailoveratms", "relation": "method", "confidence": "EXTRACTED", "source_file": "app\\src\\main\\java\\com\\kunk\\singbox\\ipc\\VpnStateStore.kt", "source_location": "L199", "weight": 1.0}, {"source": "vpnstatestore_vpnstatestore", "target": "vpnstatestore_vpnstatestore_setlastautofailoveratms", "relation": "method", "confidence": "EXTRACTED", "source_file": "app\\src\\main\\java\\com\\kunk\\singbox\\ipc\\VpnStateStore.kt", "source_location": "L201", "weight": 1.0}, {"source": "vpnstatestore_vpnstatestore", "target": "vpnstatestore_vpnstatestore_getautofailoverwindowstartatms", "relation": "method", "confidence": "EXTRACTED", "source_file": "app\\src\\main\\java\\com\\kunk\\singbox\\ipc\\VpnStateStore.kt", "source_location": "L205", "weight": 1.0}, {"source": "vpnstatestore_vpnstatestore", "target": "vpnstatestore_vpnstatestore_setautofailoverwindowstartatms", "relation": "method", "confidence": "EXTRACTED", "source_file": "app\\src\\main\\java\\com\\kunk\\singbox\\ipc\\VpnStateStore.kt", "source_location": "L207", "weight": 1.0}, {"source": "vpnstatestore_vpnstatestore", "target": "vpnstatestore_vpnstatestore_getautofailovercountinwindow", "relation": "method", "confidence": "EXTRACTED", "source_file": "app\\src\\main\\java\\com\\kunk\\singbox\\ipc\\VpnStateStore.kt", "source_location": "L211", "weight": 1.0}, {"source": "vpnstatestore_vpnstatestore", "target": "vpnstatestore_vpnstatestore_setautofailovercountinwindow", "relation": "method", "confidence": "EXTRACTED", "source_file": "app\\src\\main\\java\\com\\kunk\\singbox\\ipc\\VpnStateStore.kt", "source_location": "L213", "weight": 1.0}, {"source": "vpnstatestore_vpnstatestore", "target": "vpnstatestore_vpnstatestore_getautofailoverquarantinedtags", "relation": "method", "confidence": "EXTRACTED", "source_file": "app\\src\\main\\java\\com\\kunk\\singbox\\ipc\\VpnStateStore.kt", "source_location": "L217", "weight": 1.0}, {"source": "vpnstatestore_vpnstatestore", "target": "vpnstatestore_vpnstatestore_setautofailoverquarantinedtags", "relation": "method", "confidence": "EXTRACTED", "source_file": "app\\src\\main\\java\\com\\kunk\\singbox\\ipc\\VpnStateStore.kt", "source_location": "L219", "weight": 1.0}, {"source": "vpnstatestore_vpnstatestore", "target": "vpnstatestore_vpnstatestore_getlastautofailovernodetag", "relation": "method", "confidence": "EXTRACTED", "source_file": "app\\src\\main\\java\\com\\kunk\\singbox\\ipc\\VpnStateStore.kt", "source_location": "L223", "weight": 1.0}, {"source": "vpnstatestore_vpnstatestore", "target": "vpnstatestore_vpnstatestore_setlastautofailovernodetag", "relation": "method", "confidence": "EXTRACTED", "source_file": "app\\src\\main\\java\\com\\kunk\\singbox\\ipc\\VpnStateStore.kt", "source_location": "L225", "weight": 1.0}, {"source": "vpnstatestore_vpnstatestore", "target": "vpnstatestore_vpnstatestore_clear", "relation": "method", "confidence": "EXTRACTED", "source_file": "app\\src\\main\\java\\com\\kunk\\singbox\\ipc\\VpnStateStore.kt", "source_location": "L229", "weight": 1.0}, {"source": "vpnstatestore_vpnstatestore", "target": "vpnstatestore_vpnstatestore_clearall", "relation": "method", "confidence": "EXTRACTED", "source_file": "app\\src\\main\\java\\com\\kunk\\singbox\\ipc\\VpnStateStore.kt", "source_location": "L234", "weight": 1.0}, {"source": "vpnstatestore_vpnstatestore", "target": "vpnstatestore_vpnstatestore_clearconfig", "relation": "method", "confidence": "EXTRACTED", "source_file": "app\\src\\main\\java\\com\\kunk\\singbox\\ipc\\VpnStateStore.kt", "source_location": "L239", "weight": 1.0}, {"source": "vpnstatestore_vpnstatestore", "target": "vpnstatestore_vpnstatestore_clearruntimestate", "relation": "method", "confidence": "EXTRACTED", "source_file": "app\\src\\main\\java\\com\\kunk\\singbox\\ipc\\VpnStateStore.kt", "source_location": "L259", "weight": 1.0}, {"source": "vpnstatestore_vpnstatestore", "target": "vpnstatestore_vpnstatestore_clearautofailoverruntimestate", "relation": "method", "confidence": "EXTRACTED", "source_file": "app\\src\\main\\java\\com\\kunk\\singbox\\ipc\\VpnStateStore.kt", "source_location": "L270", "weight": 1.0}]}